README.md
setup.py
seriousity/__init__.py
seriousity/cli.py
seriousity.egg-info/PKG-INFO
seriousity.egg-info/SOURCES.txt
seriousity.egg-info/dependency_links.txt
seriousity.egg-info/entry_points.txt
seriousity.egg-info/not-zip-safe
seriousity.egg-info/top_level.txt