Metadata-Version: 2.1
Name: seriousity
Version: 1.0.1
Summary: Serious tool for serious people. I'm serious.
Home-page: https://github.com/VoIlAlex/seriousity
Author: voilalex
Author-email: ilya.vouk@gmail.com
License: UNKNOWN
Download-URL: https://github.com/VoIlAlex/archive/v1.0.1.tar.gz
Keywords: serious,people,importance,love
Platform: UNKNOWN
Classifier: Development Status :: 5 - Production/Stable
Classifier: Intended Audience :: Science/Research
Classifier: Programming Language :: Python :: 3
Classifier: Environment :: Console
